microa/__init__.py
microa/asgi.py
microa/settings.py
microa/urls.py
microa/wsgi.py
microa/__pycache__/__init__.cpython-312.pyc
microa/__pycache__/settings.cpython-312.pyc
microa/__pycache__/urls.cpython-312.pyc
microaAdmin/__init__.py
microaAdmin/admin.py
microaAdmin/apps.py
microaAdmin/models.py
microaAdmin/tests.py
microaAdmin/views.py
microaAdmin/__pycache__/__init__.cpython-312.pyc
microaAdmin/__pycache__/admin.cpython-312.pyc
microaAdmin/__pycache__/apps.cpython-312.pyc
microaAdmin/__pycache__/models.cpython-312.pyc
microaAdmin/api/serializers.py
microaAdmin/api/urls.py
microaAdmin/api/views.py
microaAdmin/api/__pycache__/serializers.cpython-312.pyc
microaAdmin/api/__pycache__/urls.cpython-312.pyc
microaAdmin/api/__pycache__/views.cpython-312.pyc
microaAdmin/migrations/0001_initial.py
microaAdmin/migrations/__init__.py
microaAdmin/migrations/__pycache__/0001_initial.cpython-312.pyc
microaAdmin/migrations/__pycache__/__init__.cpython-312.pyc
MicroA-1.4.0.dist-info/METADATA
MicroA-1.4.0.dist-info/WHEEL
MicroA-1.4.0.dist-info/top_level.txt
MicroA-1.4.0.dist-info/RECORD
